tests
travis_sphinx
